README.txt
setup.cfg
setup.py
docs/HISTORY.txt
docs/LICENSE.GPL
docs/LICENSE.txt
docs/MANUAL.txt
raptus/__init__.py
raptus.article.flash.egg-info/PKG-INFO
raptus.article.flash.egg-info/SOURCES.txt
raptus.article.flash.egg-info/dependency_links.txt
raptus.article.flash.egg-info/entry_points.txt
raptus.article.flash.egg-info/namespace_packages.txt
raptus.article.flash.egg-info/not-zip-safe
raptus.article.flash.egg-info/requires.txt
raptus.article.flash.egg-info/top_level.txt
raptus/article/__init__.py
raptus/article/flash/__init__.py
raptus/article/flash/adapters.py
raptus/article/flash/config.py
raptus/article/flash/configure.zcml
raptus/article/flash/index.py
raptus/article/flash/interfaces.py
raptus/article/flash/permissions.zcml
raptus/article/flash/browser/__init__.py
raptus/article/flash/browser/configure.zcml
raptus/article/flash/browser/flash.pt
raptus/article/flash/browser/flash.py
raptus/article/flash/browser/flash_full.gif
raptus/article/flash/browser/flash_icon.gif
raptus/article/flash/browser/flash_left.gif
raptus/article/flash/browser/flash_right.gif
raptus/article/flash/browser/flash_teaser.gif
raptus/article/flash/browser/view.pt
raptus/article/flash/browser/view.py
raptus/article/flash/content/__init__.py
raptus/article/flash/content/configure.zcml
raptus/article/flash/content/flash.py
raptus/article/flash/i18n/raptus.article-de.po
raptus/article/flash/i18n/raptus.article-fr.po
raptus/article/flash/i18n/raptus.article.pot
raptus/article/flash/profiles/default/cssregistry.xml
raptus/article/flash/profiles/default/factorytool.xml
raptus/article/flash/profiles/default/metadata.xml
raptus/article/flash/profiles/default/propertiestool.xml
raptus/article/flash/profiles/default/rolemap.xml
raptus/article/flash/profiles/default/skins.xml
raptus/article/flash/profiles/default/types.xml
raptus/article/flash/profiles/default/viewlets.xml
raptus/article/flash/profiles/default/workflows.xml
raptus/article/flash/profiles/default/types/Article.xml
raptus/article/flash/profiles/default/types/Flash.xml
raptus/article/flash/skins/raptus_article_flash/raptus.article.flash.css.dtml